LICENSE
README.md
pyproject.toml
setup.py
src/lightq/__init__.py
src/lightq/_commons.py
src/lightq/_from_context.py
src/lightq/api.py
src/lightq/exceptions.py
src/lightq/filters.py
src/lightq/logging.py
src/lightq/resolvers.py
src/lightq/utils.py
src/lightq.egg-info/PKG-INFO
src/lightq.egg-info/SOURCES.txt
src/lightq.egg-info/dependency_links.txt
src/lightq.egg-info/requires.txt
src/lightq.egg-info/top_level.txt
src/lightq/decorators/__init__.py
src/lightq/decorators/_handler.py
src/lightq/decorators/_regex.py
src/lightq/decorators/_resolve.py
src/lightq/entities/__init__.py
src/lightq/entities/_commons.py
src/lightq/entities/_element.py
src/lightq/entities/_entity.py
src/lightq/entities/_event.py
src/lightq/entities/_message.py
src/lightq/entities/_mixin.py
src/lightq/entities/_sync_message.py
src/lightq/framework/__init__.py
src/lightq/framework/_bot.py
src/lightq/framework/_context.py
src/lightq/framework/_controller.py
src/lightq/framework/_handler.py
src/lightq/framework/_router.py
src/lightq/framework/_scan.py