Metadata-Version: 2.1
Name: lightq
Version: 0.1.0
Summary: An elegant QQ bot framework based on mirai-api-http.
Author-email: ZHB <zhb2000@whu.edu.cn>
License: AGPL-3.0
Project-URL: Source, https://github.com/zhb2000/lightq
Project-URL: Bug Tracker, https://github.com/zhb2000/lightq/issues
Keywords: qq,mirai
Classifier: Programming Language :: Python :: 3
Classifier: Programming Language :: Python :: 3.10
Classifier: License :: OSI Approved :: GNU Affero General Public License v3 or later (AGPLv3+)
Classifier: Operating System :: OS Independent
Classifier: Framework :: AsyncIO
Classifier: Topic :: Internet
Classifier: Typing :: Typed
Requires-Python: >=3.10
License-File: LICENSE
